gwas_assoc/__init__.py
gwas_assoc/cli.py
gwas_assoc/commands/__init__.py
gwas_assoc/commands/validate.py
gwas_assoc/utils/__init__.py
gwas_assoc/utils/console.py
gwas_assoc_tools-0.1.2.dist-info/LICENSE
gwas_assoc_tools-0.1.2.dist-info/METADATA
gwas_assoc_tools-0.1.2.dist-info/WHEEL
gwas_assoc_tools-0.1.2.dist-info/entry_points.txt
gwas_assoc_tools-0.1.2.dist-info/RECORD
