Metadata-Version: 2.3
Name: gwas-assoc-tools
Version: 0.1.2
Summary: GWAS Association Tools
Author: Karatug Ozan Bircan
Author-email: karatugo@ebi.ac.uk
Requires-Python: >=3.10,<4.0
Classifier: Programming Language :: Python :: 3
Classifier: Programming Language :: Python :: 3.10
Classifier: Programming Language :: Python :: 3.11
Classifier: Programming Language :: Python :: 3.12
Classifier: Programming Language :: Python :: 3.13
Requires-Dist: click (>=8.0.0)
Requires-Dist: griffe (==1.6.2)
Requires-Dist: iniconfig (==2.0.0)
Requires-Dist: numpy (==2.2.3)
Requires-Dist: openpyxl (>=3.1.0,<4.0.0)
Requires-Dist: pandas (==2.2.3)
Requires-Dist: pydantic (>=2.0.0)
Requires-Dist: pytz (==2025.1)
Requires-Dist: requests (>=2.28.0,<3.0.0)
Requires-Dist: rich (>=13.0.0)
Requires-Dist: typing-extensions (==4.13.0)
Requires-Dist: tzdata (==2025.1)
